setup.py
prob_dis/__init__.py
prob_dis/bino_dis.py
prob_dis/gauss_dis.py
prob_dis/general_dis.py
prob_dis.egg-info/PKG-INFO
prob_dis.egg-info/SOURCES.txt
prob_dis.egg-info/dependency_links.txt
prob_dis.egg-info/not-zip-safe
prob_dis.egg-info/top_level.txt