Metadata-Version: 1.0
Name: prob-dis
Version: 1.0
Summary: Gaussian and Binomial Distributions included
Home-page: UNKNOWN
Author: UNKNOWN
Author-email: UNKNOWN
License: UNKNOWN
Platform: UNKNOWN
